arcgis_scraper-1.0.1.dist-info/licenses/LICENSE
arcgisscraper/__init__.py
arcgisscraper/arcgisscraper.py
arcgis_scraper-1.0.1.dist-info/METADATA
arcgis_scraper-1.0.1.dist-info/WHEEL
arcgis_scraper-1.0.1.dist-info/top_level.txt
arcgis_scraper-1.0.1.dist-info/RECORD
