Metadata-Version: 2.4
Name: arcgis-scraper
Version: 1.0.1
Summary: An ArcGIS REST API scraper
Home-page: https://github.com/pgroenbaek/arcgis-scraper
Author: Peter Grønbæk Andersen
Author-email: peter@grnbk.io
License: MIT
Classifier: Programming Language :: Python :: 3
Classifier: License :: OSI Approved :: MIT License
Classifier: Operating System :: OS Independent
Requires-Python: >=3.6
Requires-Dist: pandas>=1.0
Dynamic: author
Dynamic: author-email
Dynamic: classifier
Dynamic: description
Dynamic: description-content-type
Dynamic: home-page
Dynamic: license
Dynamic: requires-dist
Dynamic: requires-python
Dynamic: summary
